sedml/__init__.py
sedml/common.py
sedml/l1v1.py
sedml/l1v2.py
sedml/l1v3.py
sedml/l1v4.py
sedml/xml.py
sedml/tests/common.py
sedml/tests/test_biomodels.py
sedml/tests/test_sedml_examples.py
sedml-0.1.0.dist-info/LICENSE
sedml-0.1.0.dist-info/METADATA
sedml-0.1.0.dist-info/WHEEL
sedml-0.1.0.dist-info/top_level.txt
sedml-0.1.0.dist-info/RECORD
