Metadata-Version: 2.1
Name: sedml
Version: 0.1.0
Summary: A SED-ML reader based on pydantic.
Author-email: Mauro Silberberg <maurosilber@gmail.com>
License: MIT License
Project-URL: Homepage, https://github.com/maurosilber/sedml
Project-URL: Bug Tracker, https://github.com/maurosilber/sedml/issues
Keywords: SED-ML,XML,pydantic,pydantic-xml
Classifier: Intended Audience :: Developers
Classifier: Intended Audience :: Science/Research
Classifier: Topic :: Scientific/Engineering
Classifier: Topic :: Software Development :: Libraries
Classifier: Programming Language :: Python :: 3
Classifier: License :: OSI Approved :: BSD License
Classifier: Operating System :: OS Independent
Requires-Python: >=3.10
License-File: LICENSE
Requires-Dist: pydantic-xml
Requires-Dist: lxml
Requires-Dist: rich
Requires-Dist: typing-extensions
Provides-Extra: test
Requires-Dist: pytest ; extra == 'test'
Requires-Dist: biomodels >=0.2.0 ; extra == 'test'
